dataphile/__init__.py
dataphile/__main__.py
dataphile/__meta__.py
dataphile/bin/__init__.py
dataphile/bin/compress.py
dataphile/bin/decompress.py
dataphile/bin/groupby.py
dataphile/bin/gunzip.py
dataphile/bin/monitor.py
dataphile/bin/stream.py
dataphile/core/__init__.py
dataphile/core/logging.py
dataphile/core/wrappers.py
dataphile/datasets/__init__.py
dataphile/datasets/_dataset.py
dataphile/datasets/synthetic/__init__.py
dataphile/demos/__init__.py
dataphile/demos/auto_gui.py
dataphile/graphics/__init__.py
dataphile/graphics/widgets/__init__.py
dataphile/graphics/widgets/slider.py
dataphile/io/__init__.py
dataphile/io/common.py
dataphile/io/compression.py
dataphile/io/hdf5.py
dataphile/io/stream.py
dataphile/io/zlib.py
dataphile/statistics/__init__.py
dataphile/statistics/distributions.py
dataphile/statistics/regression/__init__.py
dataphile/statistics/regression/kernel.py
dataphile/statistics/regression/modeling.py
dataphile-0.2.1.dist-info/LICENSE
dataphile-0.2.1.dist-info/METADATA
dataphile-0.2.1.dist-info/WHEEL
dataphile-0.2.1.dist-info/entry_points.txt
dataphile-0.2.1.dist-info/top_level.txt
dataphile-0.2.1.dist-info/RECORD
