Metadata-Version: 2.1
Name: dataphile
Version: 0.2.1
Summary: Data analytics library and command line data-ops tools.
Home-page: https://dataphile.readthedocs.io
Author: Geoffrey Lentner
Author-email: <glentner@gmail.com>
License: Apache License
Keywords: data science tools analytics optimization
Platform: UNKNOWN
Classifier: Development Status :: 4 - Beta
Classifier: Topic :: Scientific/Engineering
Classifier: Programming Language :: Python :: 3.5
Classifier: Programming Language :: Python :: 3.6
Classifier: Programming Language :: Python :: 3.7
Classifier: License :: OSI Approved :: Apache Software License
Requires-Dist: numpy
Requires-Dist: scipy
Requires-Dist: matplotlib
Requires-Dist: seaborn
Requires-Dist: pandas
Requires-Dist: astropy
Requires-Dist: tqdm
Requires-Dist: h5py
Requires-Dist: logalpha (<2)
